LICENSE
README.txt
setup.py
AG_fft_tools/__init__.py
AG_fft_tools/convolve.py
AG_fft_tools/correlate2d.py
AG_fft_tools/psds.py
AG_image_tools/__init__.py
AG_image_tools/downsample.py
AG_image_tools/drizzle.py
AG_image_tools/radialprofile.py
agpy/PCA_tools.py
agpy/UCHIIfitter.py
agpy/__init__.py
agpy/asinh_norm.py
agpy/blackbody.py
agpy/collapse_gaussfit.py
agpy/collapseplot.py
agpy/constants.py
agpy/conversationcount.py
agpy/cubes.py
agpy/cutout.py
agpy/densitymap.py
agpy/ds9_phot.py
agpy/dust.py
agpy/gaussfitter.py
agpy/get_cutouts.py
agpy/grep.py
agpy/h2fit.py
agpy/hotwind.py
agpy/imf.py
agpy/kdist.py
agpy/lagrange_diff.py
agpy/luminosity.py
agpy/mad.py
agpy/montage
agpy/montage.sh
agpy/mpfit_custom.py
agpy/phot.ds9.ans
agpy/posang.py
agpy/powerfit.py
agpy/psf_fitter.py
agpy/pstopng
agpy/pstopng.py
agpy/pyflagger.py
agpy/query_splatalogue.py
agpy/ratosexagesimal.py
agpy/readcol.py
agpy/reg_gal2cel.py
agpy/regfile_aperture_extract.py
agpy/region_photometry.py
agpy/region_photometry_files.py
agpy/region_positions.py
agpy/regtoapo.py
agpy/regtocima.py
agpy/showspec.py
agpy/subim_gaussfit.py
agpy/timer.py
agpy.egg-info/PKG-INFO
agpy.egg-info/SOURCES.txt
agpy.egg-info/dependency_links.txt
agpy.egg-info/top_level.txt
agpy/mpfit/__init__.py
agpy/mpfit/mpfit.py
agpy/mpfit/mpfitexpr.py
contributed/__init__.py
contributed/epstopng
contributed/parallel_map.py
contributed/pngtoeps
contributed/pscompress
doc/agpy.rst
doc/conf.py
doc/contributed.rst
doc/fft_tools.rst
doc/gaussfit.rst
doc/image_tools.rst
doc/index.rst
doc/plfit.rst
doc/pyflagger.rst
doc/uchii.rst
doc/html/.buildinfo
doc/html/agpy.html
doc/html/contributed.html
doc/html/fft_tools.html
doc/html/gaussfit.html
doc/html/genindex.html
doc/html/image_tools.html
doc/html/index.html
doc/html/objects.inv
doc/html/plfit.html
doc/html/py-modindex.html
doc/html/pyflagger.html
doc/html/search.html
doc/html/searchindex.js
doc/html/uchii.html
doc/html/_images/math/04513fb09ca57647636b1992a43381b094ac1ab0.png
doc/html/_images/math/062c01af31b5cde928375daf9b07c79905fb97e6.png
