Metadata-Version: 1.0
Name: agpy
Version: 0.1.2
Summary: agpy, Adam Ginsburg's Python Code (in 0.1 for perpetuity - it won't bump up until I release something)
Home-page: http://code.google.com/p/agpy/
Author: Adam Ginsburg
Author-email: adam.ginsburg@colorado.edu
License: UNKNOWN
Platform: UNKNOWN
